gradio_audiogrid/__init__.py
gradio_audiogrid/audiogrid.py
gradio_audiogrid/audiogrid.pyi
gradio_audiogrid/requirements.txt
gradio_audiogrid/templates/component/Index-woW-0sOe.js
gradio_audiogrid/templates/component/__vite-browser-external-DYxpcVy9.js
gradio_audiogrid/templates/component/_basePickBy-hwsY6Fd-.js
gradio_audiogrid/templates/component/_baseUniq-Bz5Ju4Z5.js
gradio_audiogrid/templates/component/arc-j1uryRi5.js
gradio_audiogrid/templates/component/architectureDiagram-IEHRJDOE-gMlqRtPt.js
gradio_audiogrid/templates/component/blockDiagram-JOT3LUYC-BipknSvo.js
gradio_audiogrid/templates/component/browser-DRoBdarS.js
gradio_audiogrid/templates/component/c4Diagram-VJAJSXHY-D3VNn43D.js
gradio_audiogrid/templates/component/channel-BTYIlJ12.js
gradio_audiogrid/templates/component/chunk-4BMEZGHF-Cb0LtAyC.js
gradio_audiogrid/templates/component/chunk-A2AXSNBT-xDa0D8Li.js
gradio_audiogrid/templates/component/chunk-AEK57VVT-rAGc5QOd.js
gradio_audiogrid/templates/component/chunk-D6G4REZN-Bg8WV28Q.js
gradio_audiogrid/templates/component/chunk-RZ5BOZE2-BOIB1Jum.js
gradio_audiogrid/templates/component/chunk-XZIHB7SX-DRV3ovHq.js
gradio_audiogrid/templates/component/classDiagram-GIVACNV2-uCBAA_Ap.js
gradio_audiogrid/templates/component/classDiagram-v2-COTLJTTW-uCBAA_Ap.js
gradio_audiogrid/templates/component/clone-DBCkEXbi.js
gradio_audiogrid/templates/component/cytoscape.esm-C2cgT2B2.js
gradio_audiogrid/templates/component/dagre-OKDRZEBW-C0aQPMy4.js
gradio_audiogrid/templates/component/diagram-SSKATNLV-DXchRdjt.js
gradio_audiogrid/templates/component/diagram-VNBRO52H-DZYApu51.js
gradio_audiogrid/templates/component/erDiagram-Q7BY3M3F-Clz3eoWP.js
gradio_audiogrid/templates/component/flowDiagram-4HSFHLVR-ZYcXRTg3.js
gradio_audiogrid/templates/component/ganttDiagram-APWFNJXF-DezdQ-6U.js
gradio_audiogrid/templates/component/gitGraphDiagram-7IBYFJ6S-CKoWLViP.js
gradio_audiogrid/templates/component/graph-CZ6d8U04.js
gradio_audiogrid/templates/component/index.js
gradio_audiogrid-0.0.3.dist-info/METADATA
gradio_audiogrid-0.0.3.dist-info/WHEEL
gradio_audiogrid-0.0.3.dist-info/RECORD
