Metadata-Version: 2.4
Name: gradio_audiogrid
Version: 0.0.3
Summary: Audio Grid - Gradio component for drag and drop audio file management and merging workflows
Author-email: ahmet emre safak <aemresafak@gmail.com>, Selin Isik <selin2001a@gmail.com>
License-Expression: Apache-2.0
Keywords: audio-merger,audio-processing,gradio-custom-component,gradio-template-AudioMerger
Classifier: Development Status :: 3 - Alpha
Classifier: Operating System :: OS Independent
Classifier: Programming Language :: Python :: 3
Classifier: Programming Language :: Python :: 3 :: Only
Classifier: Programming Language :: Python :: 3.8
Classifier: Programming Language :: Python :: 3.9
Classifier: Programming Language :: Python :: 3.10
Classifier: Programming Language :: Python :: 3.11
Classifier: Topic :: Scientific/Engineering
Classifier: Topic :: Scientific/Engineering :: Artificial Intelligence
Classifier: Topic :: Scientific/Engineering :: Visualization
Requires-Python: >=3.8
Requires-Dist: gradio<6.0,>=4.0
Requires-Dist: soundfile>=0.13.1
Requires-Dist: twine>=6.1.0
Provides-Extra: dev
Requires-Dist: build; extra == 'dev'
Requires-Dist: twine; extra == 'dev'
